{
  "experiment": "ft_12_storal_transfer_clustered",
  "seed": 42,
  "early_stopping_metric": "ndcg@10",
  "exact_moral_masking": true,
  "result": {
    "model_alias": "bge_m3",
    "model_config": {
      "model_name": "BAAI/bge-m3",
      "batch_size": 8,
      "gradient_accumulation_steps": 2,
      "gradient_checkpointing": true,
      "learning_rate": 2e-05,
      "max_seq_length": 512,
      "query_instruction": "",
      "model_output_dir": "/data/lior/ft_12_storal_transfer_clustered/models/bge_m3"
    },
    "size": "s500",
    "size_config": {
      "n": 500,
      "length_range": [
        56,
        195
      ],
      "description": "MORABLES p10-p90 length-matched STORAL sample."
    },
    "storal_stats": {
      "raw_total": 1779,
      "clean_total": 1675,
      "after_length_filter": 636,
      "selected": 500,
      "unique_normalized_morals": 465,
      "exact_duplicate_moral_groups": 29,
      "exact_duplicate_moral_rows": 64,
      "length_range": [
        56,
        195
      ],
      "n_requested": 500
    },
    "train_rows": 450,
    "validation_rows": 50,
    "model_dir": "/data/lior/ft_12_storal_transfer_clustered/models/bge_m3/s500",
    "eval_doc_configs": [
      "raw",
      "direct_moral_only",
      "conceptual_abstract_only",
      "cot_proverb_only",
      "fable_direct_moral",
      "direct_moral_fable",
      "fable_conceptual_abstract",
      "conceptual_abstract_fable",
      "fable_cot_proverb",
      "cot_proverb_fable",
      "proverb_only",
      "fable_proverb",
      "proverb_fable"
    ],
    "summary_generator": "gemma4-31B",
    "eval_results": {
      "raw": {
        "summary_generator": null,
        "rankings_path": "/media/eimtest/data/lior/ParabeLink/finetuning/ft_12_storal_transfer_clustered/results/rankings/bge_m3__s500__raw__none.json",
        "metrics": {
          "MRR": 0.19477385904681768,
          "MAP": 0.15887562646439318,
          "R-Precision": 0.10391716566866266,
          "Mean Rank": 93.76646706586827,
          "Median Rank": 26.0,
          "n_queries": 668,
          "Hit@1": 0.11826347305389222,
          "Recall@1": 0.08655189620758483,
          "P@1": 0.11826347305389222,
          "NDCG@1": 0.11826347305389222,
          "Hit@5": 0.26047904191616766,
          "Recall@5": 0.20072355289421154,
          "P@5": 0.05658682634730539,
          "NDCG@5": 0.15674781806804136,
          "Hit@10": 0.3502994011976048,
          "Recall@10": 0.27509980039920157,
          "P@10": 0.0408682634730539,
          "NDCG@10": 0.1837248846917056,
          "Hit@15": 0.4041916167664671,
          "Recall@15": 0.32078343313373253,
          "P@15": 0.032235528942115774,
          "NDCG@15": 0.19743670342378153,
          "Hit@50": 0.6077844311377245,
          "Recall@50": 0.5048652694610778,
          "P@50": 0.015718562874251496,
          "NDCG@50": 0.24032254388126967,
          "Hit@100": 0.7335329341317365,
          "Recall@100": 0.6398203592814371,
          "P@100": 0.009820359281437126,
          "NDCG@100": 0.26398215030671135,
          "Hit@200": 0.842814371257485,
          "Recall@200": 0.7778942115768464,
          "P@200": 0.006115269461077844,
          "NDCG@200": 0.28590635298600053,
          "Hit@300": 0.8937125748502994,
          "Recall@300": 0.8482784431137724,
          "P@300": 0.0045359281437125755,
          "NDCG@300": 0.2963801746542682
        }
      },
      "direct_moral_only": {
        "summary_generator": "gemma4-31B",
        "rankings_path": "/media/eimtest/data/lior/ParabeLink/finetuning/ft_12_storal_transfer_clustered/results/rankings/bge_m3__s500__direct_moral_only__gemma4-31B.json",
        "metrics": {
          "MRR": 0.2900264016705047,
          "MAP": 0.23506689256714566,
          "R-Precision": 0.18243512974051898,
          "Mean Rank": 78.76946107784431,
          "Median Rank": 17.0,
          "n_queries": 668,
          "Hit@1": 0.2125748502994012,
          "Recall@1": 0.14578343313373252,
          "P@1": 0.2125748502994012,
          "NDCG@1": 0.2125748502994012,
          "Hit@5": 0.3652694610778443,
          "Recall@5": 0.2791167664670659,
          "P@5": 0.09041916167664671,
          "NDCG@5": 0.24013756387546603,
          "Hit@10": 0.4311377245508982,
          "Recall@10": 0.33987025948103794,
          "P@10": 0.055538922155688626,
          "NDCG@10": 0.26156022967498715,
          "Hit@15": 0.48952095808383234,
          "Recall@15": 0.394935129740519,
          "P@15": 0.04281437125748503,
          "NDCG@15": 0.27770606397554093,
          "Hit@50": 0.6721556886227545,
          "Recall@50": 0.5909431137724551,
          "P@50": 0.01907185628742515,
          "NDCG@50": 0.32249123406281116,
          "Hit@100": 0.7664670658682635,
          "Recall@100": 0.7029191616766467,
          "P@100": 0.01125748502994012,
          "NDCG@100": 0.3425730528440333,
          "Hit@200": 0.8667664670658682,
          "Recall@200": 0.8226047904191617,
          "P@200": 0.006646706586826347,
          "NDCG@200": 0.36159299547329377,
          "Hit@300": 0.9161676646706587,
          "Recall@300": 0.8852045908183633,
          "P@300": 0.004785429141716567,
          "NDCG@300": 0.37054354514925825
        }
      },
      "conceptual_abstract_only": {
        "summary_generator": "gemma4-31B",
        "rankings_path": "/media/eimtest/data/lior/ParabeLink/finetuning/ft_12_storal_transfer_clustered/results/rankings/bge_m3__s500__conceptual_abstract_only__gemma4-31B.json",
        "metrics": {
          "MRR": 0.2565651507529153,
          "MAP": 0.20674803786774515,
          "R-Precision": 0.1434880239520958,
          "Mean Rank": 82.937125748503,
          "Median Rank": 19.5,
          "n_queries": 668,
          "Hit@1": 0.1691616766467066,
          "Recall@1": 0.11526946107784432,
          "P@1": 0.1691616766467066,
          "NDCG@1": 0.1691616766467066,
          "Hit@5": 0.3383233532934132,
          "Recall@5": 0.26062874251497004,
          "P@5": 0.07994011976047904,
          "NDCG@5": 0.2113550742678924,
          "Hit@10": 0.4221556886227545,
          "Recall@10": 0.3383233532934132,
          "P@10": 0.05284431137724552,
          "NDCG@10": 0.23945121813986367,
          "Hit@15": 0.46706586826347307,
          "Recall@15": 0.37859281437125747,
          "P@15": 0.04001996007984032,
          "NDCG@15": 0.2517663973439647,
          "Hit@50": 0.6317365269461078,
          "Recall@50": 0.5509730538922155,
          "P@50": 0.01787425149700599,
          "NDCG@50": 0.29231779068962155,
          "Hit@100": 0.7365269461077845,
          "Recall@100": 0.6685379241516967,
          "P@100": 0.01095808383233533,
          "NDCG@100": 0.3141067918689593,
          "Hit@200": 0.8517964071856288,
          "Recall@200": 0.8013223552894211,
          "P@200": 0.006474550898203593,
          "NDCG@200": 0.3343424126326904,
          "Hit@300": 0.9221556886227545,
          "Recall@300": 0.8907185628742516,
          "P@300": 0.004775449101796407,
          "NDCG@300": 0.3467827010467477
        }
      },
      "cot_proverb_only": {
        "summary_generator": "gemma4-31B",
        "rankings_path": "/media/eimtest/data/lior/ParabeLink/finetuning/ft_12_storal_transfer_clustered/results/rankings/bge_m3__s500__cot_proverb_only__gemma4-31B.json",
        "metrics": {
          "MRR": 0.19788477791768974,
          "MAP": 0.16006228941230102,
          "R-Precision": 0.10521457085828342,
          "Mean Rank": 114.62574850299401,
          "Median Rank": 39.0,
          "n_queries": 668,
          "Hit@1": 0.12574850299401197,
          "Recall@1": 0.07899201596806386,
          "P@1": 0.12574850299401197,
          "NDCG@1": 0.12574850299401197,
          "Hit@5": 0.26047904191616766,
          "Recall@5": 0.20464071856287425,
          "P@5": 0.06676646706586827,
          "NDCG@5": 0.16247573462774262,
          "Hit@10": 0.3383233532934132,
          "Recall@10": 0.26694111776447105,
          "P@10": 0.04401197604790419,
          "NDCG@10": 0.18502397432362708,
          "Hit@15": 0.37574850299401197,
          "Recall@15": 0.3051147704590818,
          "P@15": 0.033832335329341316,
          "NDCG@15": 0.19664180229261374,
          "Hit@50": 0.5404191616766467,
          "Recall@50": 0.4641217564870259,
          "P@50": 0.015508982035928143,
          "NDCG@50": 0.23362744350851034,
          "Hit@100": 0.6706586826347305,
          "Recall@100": 0.5864770459081836,
          "P@100": 0.00964071856287425,
          "NDCG@100": 0.2554574693157508,
          "Hit@200": 0.7904191616766467,
          "Recall@200": 0.7256986027944111,
          "P@200": 0.005965568862275448,
          "NDCG@200": 0.2773083561783823,
          "Hit@300": 0.8712574850299402,
          "Recall@300": 0.8234031936127744,
          "P@300": 0.004446107784431138,
          "NDCG@300": 0.2906602963301226
        }
      },
      "fable_direct_moral": {
        "summary_generator": "gemma4-31B",
        "rankings_path": "/media/eimtest/data/lior/ParabeLink/finetuning/ft_12_storal_transfer_clustered/results/rankings/bge_m3__s500__fable_direct_moral__gemma4-31B.json",
        "metrics": {
          "MRR": 0.3182174257671981,
          "MAP": 0.26437330043428986,
          "R-Precision": 0.20000000000000004,
          "Mean Rank": 61.77395209580838,
          "Median Rank": 13.0,
          "n_queries": 668,
          "Hit@1": 0.23053892215568864,
          "Recall@1": 0.16294910179640718,
          "P@1": 0.23053892215568864,
          "NDCG@1": 0.23053892215568864,
          "Hit@5": 0.4101796407185629,
          "Recall@5": 0.324625748502994,
          "P@5": 0.09940119760479042,
          "NDCG@5": 0.2720800453070234,
          "Hit@10": 0.4805389221556886,
          "Recall@10": 0.3965069860279441,
          "P@10": 0.061377245508982034,
          "NDCG@10": 0.2972809286449843,
          "Hit@15": 0.5494011976047904,
          "Recall@15": 0.46027944111776453,
          "P@15": 0.04730538922155689,
          "NDCG@15": 0.31551751286839635,
          "Hit@50": 0.7050898203592815,
          "Recall@50": 0.6283932135728544,
          "P@50": 0.020149700598802396,
          "NDCG@50": 0.35564892256827324,
          "Hit@100": 0.8173652694610778,
          "Recall@100": 0.7533433133732536,
          "P@100": 0.011961077844311378,
          "NDCG@100": 0.37777434498104306,
          "Hit@200": 0.9041916167664671,
          "Recall@200": 0.8594560878243513,
          "P@200": 0.006856287425149701,
          "NDCG@200": 0.39442568853096216,
          "Hit@300": 0.9476047904191617,
          "Recall@300": 0.9199101796407185,
          "P@300": 0.004925149700598802,
          "NDCG@300": 0.4030915567381677
        }
      },
      "direct_moral_fable": {
        "summary_generator": "gemma4-31B",
        "rankings_path": "/media/eimtest/data/lior/ParabeLink/finetuning/ft_12_storal_transfer_clustered/results/rankings/bge_m3__s500__direct_moral_fable__gemma4-31B.json",
        "metrics": {
          "MRR": 0.3191552008022447,
          "MAP": 0.2657958444461346,
          "R-Precision": 0.19795409181636728,
          "Mean Rank": 62.34580838323353,
          "Median Rank": 11.0,
          "n_queries": 668,
          "Hit@1": 0.23203592814371257,
          "Recall@1": 0.16414670658682637,
          "P@1": 0.23203592814371257,
          "NDCG@1": 0.23203592814371257,
          "Hit@5": 0.4041916167664671,
          "Recall@5": 0.32307884231536926,
          "P@5": 0.09850299401197604,
          "NDCG@5": 0.27127233270082074,
          "Hit@10": 0.4865269461077844,
          "Recall@10": 0.40209580838323356,
          "P@10": 0.06122754491017965,
          "NDCG@10": 0.29920549627265114,
          "Hit@15": 0.5508982035928144,
          "Recall@15": 0.46424650698602793,
          "P@15": 0.04810379241516966,
          "NDCG@15": 0.3181244893123457,
          "Hit@50": 0.7050898203592815,
          "Recall@50": 0.6291417165668662,
          "P@50": 0.020209580838323353,
          "NDCG@50": 0.3576181003336965,
          "Hit@100": 0.8098802395209581,
          "Recall@100": 0.7463572854291417,
          "P@100": 0.01187125748502994,
          "NDCG@100": 0.3784485035455627,
          "Hit@200": 0.8997005988023952,
          "Recall@200": 0.8581836327345309,
          "P@200": 0.00688622754491018,
          "NDCG@200": 0.3961778654259251,
          "Hit@300": 0.9476047904191617,
          "Recall@300": 0.9199101796407185,
          "P@300": 0.004915169660678643,
          "NDCG@300": 0.4047641376212513
        }
      },
      "fable_conceptual_abstract": {
        "summary_generator": "gemma4-31B",
        "rankings_path": "/media/eimtest/data/lior/ParabeLink/finetuning/ft_12_storal_transfer_clustered/results/rankings/bge_m3__s500__fable_conceptual_abstract__gemma4-31B.json",
        "metrics": {
          "MRR": 0.3089680623044315,
          "MAP": 0.25159087085969034,
          "R-Precision": 0.18288423153692612,
          "Mean Rank": 63.455089820359284,
          "Median Rank": 12.0,
          "n_queries": 668,
          "Hit@1": 0.22305389221556887,
          "Recall@1": 0.15563872255489022,
          "P@1": 0.22305389221556887,
          "NDCG@1": 0.22305389221556887,
          "Hit@5": 0.4041916167664671,
          "Recall@5": 0.3137475049900199,
          "P@5": 0.09401197604790419,
          "NDCG@5": 0.2597397505496684,
          "Hit@10": 0.47904191616766467,
          "Recall@10": 0.38552894211576844,
          "P@10": 0.058682634730538925,
          "NDCG@10": 0.28494205506582493,
          "Hit@15": 0.5284431137724551,
          "Recall@15": 0.4390968063872255,
          "P@15": 0.045109780439121755,
          "NDCG@15": 0.3010094888395742,
          "Hit@50": 0.7335329341317365,
          "Recall@50": 0.6480788423153692,
          "P@50": 0.02038922155688623,
          "NDCG@50": 0.3495572842263627,
          "Hit@100": 0.8098802395209581,
          "Recall@100": 0.7430888223552894,
          "P@100": 0.011811377245508983,
          "NDCG@100": 0.367019786399812,
          "Hit@200": 0.8847305389221557,
          "Recall@200": 0.8407934131736526,
          "P@200": 0.006729041916167666,
          "NDCG@200": 0.38255383042360713,
          "Hit@300": 0.9446107784431138,
          "Recall@300": 0.915369261477046,
          "P@300": 0.0048652694610778445,
          "NDCG@300": 0.39289342974321856
        }
      },
      "conceptual_abstract_fable": {
        "summary_generator": "gemma4-31B",
        "rankings_path": "/media/eimtest/data/lior/ParabeLink/finetuning/ft_12_storal_transfer_clustered/results/rankings/bge_m3__s500__conceptual_abstract_fable__gemma4-31B.json",
        "metrics": {
          "MRR": 0.3111585393833878,
          "MAP": 0.25377053614550665,
          "R-Precision": 0.18188622754491016,
          "Mean Rank": 62.285928143712574,
          "Median Rank": 12.0,
          "n_queries": 668,
          "Hit@1": 0.218562874251497,
          "Recall@1": 0.15351796407185628,
          "P@1": 0.218562874251497,
          "NDCG@1": 0.218562874251497,
          "Hit@5": 0.41467065868263475,
          "Recall@5": 0.32734530938123757,
          "P@5": 0.09640718562874252,
          "NDCG@5": 0.2652149580170606,
          "Hit@10": 0.4820359281437126,
          "Recall@10": 0.3896207584830339,
          "P@10": 0.06017964071856287,
          "NDCG@10": 0.2883425251700557,
          "Hit@15": 0.5434131736526946,
          "Recall@15": 0.45444111776447105,
          "P@15": 0.04640718562874251,
          "NDCG@15": 0.3071340245927122,
          "Hit@50": 0.7290419161676647,
          "Recall@50": 0.6460329341317366,
          "P@50": 0.02026946107784431,
          "NDCG@50": 0.3517411274996243,
          "Hit@100": 0.8218562874251497,
          "Recall@100": 0.7533682634730539,
          "P@100": 0.011931137724550896,
          "NDCG@100": 0.3713298706295725,
          "Hit@200": 0.8907185628742516,
          "Recall@200": 0.8475299401197606,
          "P@200": 0.006766467065868264,
          "NDCG@200": 0.38632793888834027,
          "Hit@300": 0.9416167664670658,
          "Recall@300": 0.9108782435129741,
          "P@300": 0.004835329341317366,
          "NDCG@300": 0.3951244189417347
        }
      },
      "fable_cot_proverb": {
        "summary_generator": "gemma4-31B",
        "rankings_path": "/media/eimtest/data/lior/ParabeLink/finetuning/ft_12_storal_transfer_clustered/results/rankings/bge_m3__s500__fable_cot_proverb__gemma4-31B.json",
        "metrics": {
          "MRR": 0.27274731978125377,
          "MAP": 0.22973744672337063,
          "R-Precision": 0.15853293413173652,
          "Mean Rank": 72.3997005988024,
          "Median Rank": 16.0,
          "n_queries": 668,
          "Hit@1": 0.18113772455089822,
          "Recall@1": 0.12644710578842316,
          "P@1": 0.18113772455089822,
          "NDCG@1": 0.18113772455089822,
          "Hit@5": 0.3727544910179641,
          "Recall@5": 0.299750499001996,
          "P@5": 0.09281437125748503,
          "NDCG@5": 0.2393133956895578,
          "Hit@10": 0.45209580838323354,
          "Recall@10": 0.3711576846307385,
          "P@10": 0.05793413173652695,
          "NDCG@10": 0.26485651109533875,
          "Hit@15": 0.4940119760479042,
          "Recall@15": 0.4088323353293414,
          "P@15": 0.04341317365269461,
          "NDCG@15": 0.2764796744470063,
          "Hit@50": 0.6601796407185628,
          "Recall@50": 0.5847305389221557,
          "P@50": 0.018772455089820356,
          "NDCG@50": 0.31681759130824444,
          "Hit@100": 0.7964071856287425,
          "Recall@100": 0.7302894211576846,
          "P@100": 0.01155688622754491,
          "NDCG@100": 0.3426341070090505,
          "Hit@200": 0.8787425149700598,
          "Recall@200": 0.8333582834331337,
          "P@200": 0.006691616766467067,
          "NDCG@200": 0.35922507942734655,
          "Hit@300": 0.9326347305389222,
          "Recall@300": 0.8997255489021956,
          "P@300": 0.004815369261477046,
          "NDCG@300": 0.3685615788767322
        }
      },
      "cot_proverb_fable": {
        "summary_generator": "gemma4-31B",
        "rankings_path": "/media/eimtest/data/lior/ParabeLink/finetuning/ft_12_storal_transfer_clustered/results/rankings/bge_m3__s500__cot_proverb_fable__gemma4-31B.json",
        "metrics": {
          "MRR": 0.29335803196206817,
          "MAP": 0.24078440735975584,
          "R-Precision": 0.17687125748502994,
          "Mean Rank": 72.37275449101796,
          "Median Rank": 15.0,
          "n_queries": 668,
          "Hit@1": 0.2125748502994012,
          "Recall@1": 0.1461576846307385,
          "P@1": 0.2125748502994012,
          "NDCG@1": 0.2125748502994012,
          "Hit@5": 0.3787425149700599,
          "Recall@5": 0.30087325349301397,
          "P@5": 0.09371257485029941,
          "NDCG@5": 0.25017916746116525,
          "Hit@10": 0.44610778443113774,
          "Recall@10": 0.3619261477045908,
          "P@10": 0.056586826347305386,
          "NDCG@10": 0.2715179607703173,
          "Hit@15": 0.5044910179640718,
          "Recall@15": 0.4160678642714571,
          "P@15": 0.043812375249501,
          "NDCG@15": 0.28787057107813596,
          "Hit@50": 0.6766467065868264,
          "Recall@50": 0.5878243512974052,
          "P@50": 0.01868263473053892,
          "NDCG@50": 0.3271514591911983,
          "Hit@100": 0.7934131736526946,
          "Recall@100": 0.7275698602794411,
          "P@100": 0.01155688622754491,
          "NDCG@100": 0.35219920379034175,
          "Hit@200": 0.8787425149700598,
          "Recall@200": 0.8357285429141716,
          "P@200": 0.006699101796407185,
          "NDCG@200": 0.369392974900131,
          "Hit@300": 0.9341317365269461,
          "Recall@300": 0.8979790419161677,
          "P@300": 0.004790419161676647,
          "NDCG@300": 0.3781018490450069
        }
      },
      "proverb_only": {
        "summary_generator": "gemma4-31B",
        "rankings_path": "/media/eimtest/data/lior/ParabeLink/finetuning/ft_12_storal_transfer_clustered/results/rankings/bge_m3__s500__proverb_only__gemma4-31B.json",
        "metrics": {
          "MRR": 0.012556033720579743,
          "MAP": 0.009350810174847943,
          "R-Precision": 0.0012475049900199599,
          "Mean Rank": 317.0284431137725,
          "Median Rank": 295.5,
          "n_queries": 668,
          "Hit@1": 0.0,
          "Recall@1": 0.0,
          "P@1": 0.0,
          "NDCG@1": 0.0,
          "Hit@5": 0.010479041916167664,
          "Recall@5": 0.006487025948103793,
          "P@5": 0.0020958083832335332,
          "NDCG@5": 0.0035463561366753556,
          "Hit@10": 0.02245508982035928,
          "Recall@10": 0.013073852295409184,
          "P@10": 0.002245508982035928,
          "NDCG@10": 0.006016805179189878,
          "Hit@15": 0.0374251497005988,
          "Recall@15": 0.019411177644710582,
          "P@15": 0.0024950099800399197,
          "NDCG@15": 0.00813524040307329,
          "Hit@50": 0.1062874251497006,
          "Recall@50": 0.06152694610778443,
          "P@50": 0.002335329341317365,
          "NDCG@50": 0.017954707195283758,
          "Hit@100": 0.18712574850299402,
          "Recall@100": 0.12524950099800397,
          "P@100": 0.0021107784431137725,
          "NDCG@100": 0.029213355585625978,
          "Hit@200": 0.35778443113772457,
          "Recall@200": 0.2666666666666667,
          "P@200": 0.00218562874251497,
          "NDCG@200": 0.051143602505851926,
          "Hit@300": 0.5074850299401198,
          "Recall@300": 0.413872255489022,
          "P@300": 0.0023053892215568863,
          "NDCG@300": 0.07211897443912028
        }
      },
      "fable_proverb": {
        "summary_generator": "gemma4-31B",
        "rankings_path": "/media/eimtest/data/lior/ParabeLink/finetuning/ft_12_storal_transfer_clustered/results/rankings/bge_m3__s500__fable_proverb__gemma4-31B.json",
        "metrics": {
          "MRR": 0.1953838202920045,
          "MAP": 0.15812512884498414,
          "R-Precision": 0.09593313373253493,
          "Mean Rank": 92.7125748502994,
          "Median Rank": 27.0,
          "n_queries": 668,
          "Hit@1": 0.11826347305389222,
          "Recall@1": 0.08315868263473053,
          "P@1": 0.11826347305389222,
          "NDCG@1": 0.11826347305389222,
          "Hit@5": 0.25299401197604793,
          "Recall@5": 0.19573353293413173,
          "P@5": 0.05508982035928144,
          "NDCG@5": 0.15477561210286853,
          "Hit@10": 0.34281437125748504,
          "Recall@10": 0.26928642714570855,
          "P@10": 0.04011976047904192,
          "NDCG@10": 0.1817203864108514,
          "Hit@15": 0.41467065868263475,
          "Recall@15": 0.32619760479041915,
          "P@15": 0.03263473053892215,
          "NDCG@15": 0.1984214240366517,
          "Hit@50": 0.6002994011976048,
          "Recall@50": 0.4991017964071856,
          "P@50": 0.01538922155688623,
          "NDCG@50": 0.23847087381680723,
          "Hit@100": 0.7290419161676647,
          "Recall@100": 0.635254491017964,
          "P@100": 0.009790419161676648,
          "NDCG@100": 0.26307755213747724,
          "Hit@200": 0.8547904191616766,
          "Recall@200": 0.7878243512974051,
          "P@200": 0.0061751497005988025,
          "NDCG@200": 0.28708740244132686,
          "Hit@300": 0.8967065868263473,
          "Recall@300": 0.8535179640718562,
          "P@300": 0.004565868263473055,
          "NDCG@300": 0.29698866349321384
        }
      },
      "proverb_fable": {
        "summary_generator": "gemma4-31B",
        "rankings_path": "/media/eimtest/data/lior/ParabeLink/finetuning/ft_12_storal_transfer_clustered/results/rankings/bge_m3__s500__proverb_fable__gemma4-31B.json",
        "metrics": {
          "MRR": 0.19051001381462623,
          "MAP": 0.15370707620125312,
          "R-Precision": 0.09368762475049901,
          "Mean Rank": 92.51946107784431,
          "Median Rank": 25.5,
          "n_queries": 668,
          "Hit@1": 0.1062874251497006,
          "Recall@1": 0.07504990019960078,
          "P@1": 0.1062874251497006,
          "NDCG@1": 0.1062874251497006,
          "Hit@5": 0.25299401197604793,
          "Recall@5": 0.1959830339321357,
          "P@5": 0.055688622754491025,
          "NDCG@5": 0.15186905388037905,
          "Hit@10": 0.3398203592814371,
          "Recall@10": 0.268937125748503,
          "P@10": 0.03967065868263473,
          "NDCG@10": 0.17806172707269036,
          "Hit@15": 0.405688622754491,
          "Recall@15": 0.3196606786427146,
          "P@15": 0.032235528942115774,
          "NDCG@15": 0.19345706031943224,
          "Hit@50": 0.6002994011976048,
          "Recall@50": 0.49957584830339324,
          "P@50": 0.015449101796407187,
          "NDCG@50": 0.23518773579308214,
          "Hit@100": 0.7320359281437125,
          "Recall@100": 0.6408183632734531,
          "P@100": 0.009865269461077844,
          "NDCG@100": 0.26061938561041925,
          "Hit@200": 0.8517964071856288,
          "Recall@200": 0.7847804391217565,
          "P@200": 0.006160179640718563,
          "NDCG@200": 0.2833595302860247,
          "Hit@300": 0.8997005988023952,
          "Recall@300": 0.8546906187624751,
          "P@300": 0.004545908183632735,
          "NDCG@300": 0.2936546260195465
        }
      }
    }
  }
}